pacifica/__init__.py
pacifica_namespace-0.0.2.dist-info/LICENSE
pacifica_namespace-0.0.2.dist-info/METADATA
pacifica_namespace-0.0.2.dist-info/WHEEL
pacifica_namespace-0.0.2.dist-info/top_level.txt
pacifica_namespace-0.0.2.dist-info/RECORD
