Metadata-Version: 2.1
Name: pacifica-namespace
Version: 0.0.2
Summary: Pacifica Namespace Package
Home-page: https://github.com/pacifica/pacifica-namespace/
Author: David Brown
Author-email: dmlb2000@gmail.com
License: UNKNOWN
Platform: UNKNOWN
